django_pkgconf-0.5.0.dist-info/licenses/LICENSE
pkgconf/__init__.py
django_pkgconf-0.5.0.dist-info/METADATA
django_pkgconf-0.5.0.dist-info/WHEEL
django_pkgconf-0.5.0.dist-info/top_level.txt
django_pkgconf-0.5.0.dist-info/RECORD
